odoo/addons/so_pricelist_lines_view/README.rst
odoo/addons/so_pricelist_lines_view/__init__.py
odoo/addons/so_pricelist_lines_view/__manifest__.py
odoo/addons/so_pricelist_lines_view/i18n/es.po
odoo/addons/so_pricelist_lines_view/static/description/icon.png
odoo/addons/so_pricelist_lines_view/views/pricelist_views.xml
odoo_addon_so_pricelist_lines_view-15.0.1.0.1.dist-info/METADATA
odoo_addon_so_pricelist_lines_view-15.0.1.0.1.dist-info/WHEEL
odoo_addon_so_pricelist_lines_view-15.0.1.0.1.dist-info/top_level.txt
odoo_addon_so_pricelist_lines_view-15.0.1.0.1.dist-info/RECORD
